MANIFEST.in
setup.cfg
setup.py
Products/.__init__.py.swp
Products/__init__.py
Products.ATFlashMovie.egg-info/PKG-INFO
Products.ATFlashMovie.egg-info/SOURCES.txt
Products.ATFlashMovie.egg-info/dependency_links.txt
Products.ATFlashMovie.egg-info/namespace_packages.txt
Products.ATFlashMovie.egg-info/not-zip-safe
Products.ATFlashMovie.egg-info/requires.txt
Products.ATFlashMovie.egg-info/top_level.txt
Products/ATFlashMovie/.CHANGES.txt.swp
Products/ATFlashMovie/.README.txt.swp
Products/ATFlashMovie/.version.txt.swp
Products/ATFlashMovie/ATFlashMovie.py
Products/ATFlashMovie/CHANGES.txt
Products/ATFlashMovie/IGNORE.txt
Products/ATFlashMovie/LICENSE.GPL
Products/ATFlashMovie/README.txt
Products/ATFlashMovie/__init__.py
Products/ATFlashMovie/config.py
Products/ATFlashMovie/configure.zcml
Products/ATFlashMovie/interfaces.py
Products/ATFlashMovie/setuphandlers.py
Products/ATFlashMovie/swfHeaderData.py
Products/ATFlashMovie/version.txt
Products/ATFlashMovie/browser/__init__.py
Products/ATFlashMovie/browser/browser.py
Products/ATFlashMovie/browser/collage_portlet.pt
Products/ATFlashMovie/browser/collage_standard.pt
Products/ATFlashMovie/browser/configure.zcml
Products/ATFlashMovie/browser/portlet.pt
Products/ATFlashMovie/browser/portlet.py
Products/ATFlashMovie/i18n/.flashmovie-bg.po.swp
Products/ATFlashMovie/i18n/.flashmovie-en.po.swp
Products/ATFlashMovie/i18n/.flashmovie-plone-bg.po.swp
Products/ATFlashMovie/i18n/.flashmovie-plone.pot.swp
Products/ATFlashMovie/i18n/.flashmovie.pot.swp
Products/ATFlashMovie/i18n/flashmovie-bg.po
Products/ATFlashMovie/i18n/flashmovie-de.po
Products/ATFlashMovie/i18n/flashmovie-en.po
Products/ATFlashMovie/i18n/flashmovie-fr.po
Products/ATFlashMovie/i18n/flashmovie-plone-bg.po
Products/ATFlashMovie/i18n/flashmovie-plone-en.po
Products/ATFlashMovie/i18n/flashmovie-plone-fr.po
Products/ATFlashMovie/i18n/flashmovie-plone.pot
Products/ATFlashMovie/i18n/flashmovie.pot
Products/ATFlashMovie/profiles/default/factorytool.xml
Products/ATFlashMovie/profiles/default/import_steps.xml
Products/ATFlashMovie/profiles/default/portlets.xml
Products/ATFlashMovie/profiles/default/skins.xml
Products/ATFlashMovie/profiles/default/types.xml
Products/ATFlashMovie/profiles/default/types/FlashMovie.xml
Products/ATFlashMovie/skins/flashmovie/flashmovie_macros.pt
