Metadata-Version: 1.0
Name: Products.ATFlashMovie
Version: 1.1
Summary: A Flash content-type and extra views for Plone.
Home-page: http://plone.org/products/atflashmovie
Author: Jean-Charles Rogez
Author-email: jeancharles.rogez@free.fr
License: GPL
Keywords: plone flash
Platform: UNKNOWN
Classifier: Programming Language :: Python
Classifier: Framework :: Plone
Classifier: License :: OSI Approved :: GNU General Public License (GPL)
